pyclhash/__init__.py
pyclhash/backends/__init__.py
pyclhash/backends/cffi/__init__.py
pyclhash/backends/cffi/_clhash.pypy39-pp73-x86_64-linux-gnu.so
pyclhash/backends/cffi/build.py
pyclhash/backends/cython/__init__.py
pyclhash/backends/cython/_clhash.c
pyclhash/backends/cython/_clhash.pypy39-pp73-x86_64-linux-gnu.so
pyclhash/backends/cython/_clhash.pyx
pyclhash/backends/cython/clhash.pxd
pyclhash-0.1.1.dist-info/METADATA
pyclhash-0.1.1.dist-info/WHEEL
pyclhash-0.1.1.dist-info/top_level.txt
pyclhash-0.1.1.dist-info/RECORD
