Metadata-Version: 2.1
Name: pyclhash
Version: 0.1.1
Summary: python binding for clhash
Home-page: https://github.com/synodriver/pyclhash
Author: synodriver
Author-email: diguohuangjiajinweijun@gmail.com
License: BSD
Keywords: hash,clhash
Classifier: Development Status :: 4 - Beta
Classifier: Operating System :: OS Independent
Classifier: License :: OSI Approved :: BSD License
Classifier: Programming Language :: C
Classifier: Programming Language :: Cython
Classifier: Programming Language :: Python
Classifier: Programming Language :: Python :: 3.6
Classifier: Programming Language :: Python :: 3.7
Classifier: Programming Language :: Python :: 3.8
Classifier: Programming Language :: Python :: 3.9
Classifier: Programming Language :: Python :: 3.10
Classifier: Programming Language :: Python :: 3.11
Classifier: Programming Language :: Python :: Implementation :: CPython
Classifier: Programming Language :: Python :: Implementation :: PyPy
Requires-Python: >=3.6
Requires-Dist: cffi (>=1.0.0)
